iseqclinicaltrials/ContentGetter.py
iseqclinicaltrials/DatabaseInitializer.py
iseqclinicaltrials/DatabaseQuery.py
iseqclinicaltrials/StudiesFilter.py
iseqclinicaltrials/__init__.py
iseqclinicaltrials/get_content_as_sql.py
iseqclinicaltrials/get_records.py
iseqclinicaltrials/resources/asian_countries.txt
iseqclinicaltrials/test/__init__.py
iseqclinicaltrials-0.0.3.dist-info/LICENSE
iseqclinicaltrials-0.0.3.dist-info/METADATA
iseqclinicaltrials-0.0.3.dist-info/WHEEL
iseqclinicaltrials-0.0.3.dist-info/entry_points.txt
iseqclinicaltrials-0.0.3.dist-info/top_level.txt
iseqclinicaltrials-0.0.3.dist-info/RECORD
