Metadata-Version: 2.1
Name: iseqclinicaltrials
Version: 0.0.3
Summary: Meta data for intelliseq
Home-page: https://gitlab.com/intelliseq/iseqclinicaltrials
Author: motfalo
Author-email: olaf.tomaszewski@intelliseq.pl
Classifier: Programming Language :: Python :: 3
Classifier: License :: Free for non-commercial use
Classifier: Operating System :: OS Independent
Requires-Python: >=3.6
License-File: LICENSE
Requires-Dist: pytest >=6.0.0
Requires-Dist: pandas >=2.0.3
Requires-Dist: sqlalchemy >=2.0.19
Requires-Dist: numpy >=1.25.1
Requires-Dist: requests >=2.31.0
